LICENSE
README.md
pyproject.toml
setup.cfg
setup.py
src/msdss_models_sklearn/__init__.py
src/msdss_models_sklearn/core.py
src/msdss_models_sklearn/defaults.py
src/msdss_models_sklearn/tools.py
src/msdss_models_sklearn.egg-info/PKG-INFO
src/msdss_models_sklearn.egg-info/SOURCES.txt
src/msdss_models_sklearn.egg-info/dependency_links.txt
src/msdss_models_sklearn.egg-info/requires.txt
src/msdss_models_sklearn.egg-info/top_level.txt