Metadata-Version: 2.1
Name: msdss-models-sklearn
Version: 0.0.2
Summary: Scikit-learn models for the Modular Spatial Decision Support Systems (MSDSS) framework
Home-page: https://github.com/rrwen/msdss-models-sklearn
Author: Richard Wen
Author-email: rrwen.dev@gmail.com
License: UNKNOWN
Project-URL: Bug Tracker, https://github.com/rrwen/msdss-models-sklearn/issues
Platform: UNKNOWN
Classifier: Programming Language :: Python :: 3
Classifier: License :: OSI Approved :: MIT License
Classifier: Operating System :: OS Independent
Requires-Python: >=3.8
License-File: LICENSE
